<annotation verified="yes">
	<folder>华伟图像处理</folder>
	<filename>IMG_1585(2).jpg</filename>
	<path>C:\Users\Lenovo\Desktop\华伟图像处理\IMG_1585(2).jpg</path>
	<source>
		<database>Unknown</database>
	</source>
	<size>
		<width>2394</width>
		<height>1779</height>
		<depth>3</depth>
	</size>
	<segmented>0</segmented>
	<object>
		<name>nothing</name>
		<pose>Unspecified</pose>
		<truncated>0</truncated>
		<difficult>0</difficult>
		<bndbox>
			<xmin>617</xmin>
			<ymin>502</ymin>
			<xmax>677</xmax>
			<ymax>680</ymax>
		</bndbox>
	</object>
	<object>
		<name>nothing</name>
		<pose>Unspecified</pose>
		<truncated>0</truncated>
		<difficult>0</difficult>
		<bndbox>
			<xmin>758</xmin>
			<ymin>497</ymin>
			<xmax>818</xmax>
			<ymax>675</ymax>
		</bndbox>
	</object>
	<object>
		<name>nothing</name>
		<pose>Unspecified</pose>
		<truncated>0</truncated>
		<difficult>0</difficult>
		<bndbox>
			<xmin>899</xmin>
			<ymin>497</ymin>
			<xmax>959</xmax>
			<ymax>675</ymax>
		</bndbox>
	</object>
	<object>
		<name>nothing</name>
		<pose>Unspecified</pose>
		<truncated>0</truncated>
		<difficult>0</difficult>
		<bndbox>
			<xmin>1058</xmin>
			<ymin>489</ymin>
			<xmax>1118</xmax>
			<ymax>667</ymax>
		</bndbox>
	</object>
	<object>
		<name>nothing</name>
		<pose>Unspecified</pose>
		<truncated>0</truncated>
		<difficult>0</difficult>
		<bndbox>
			<xmin>1199</xmin>
			<ymin>482</ymin>
			<xmax>1259</xmax>
			<ymax>660</ymax>
		</bndbox>
	</object>
	<object>
		<name>nothing</name>
		<pose>Unspecified</pose>
		<truncated>0</truncated>
		<difficult>0</difficult>
		<bndbox>
			<xmin>1350</xmin>
			<ymin>487</ymin>
			<xmax>1410</xmax>
			<ymax>665</ymax>
		</bndbox>
	</object>
	<object>
		<name>nothing</name>
		<pose>Unspecified</pose>
		<truncated>0</truncated>
		<difficult>0</difficult>
		<bndbox>
			<xmin>1512</xmin>
			<ymin>478</ymin>
			<xmax>1572</xmax>
			<ymax>656</ymax>
		</bndbox>
	</object>
	<object>
		<name>nothing</name>
		<pose>Unspecified</pose>
		<truncated>0</truncated>
		<difficult>0</difficult>
		<bndbox>
			<xmin>1661</xmin>
			<ymin>461</ymin>
			<xmax>1721</xmax>
			<ymax>639</ymax>
		</bndbox>
	</object>
	<object>
		<name>nothing</name>
		<pose>Unspecified</pose>
		<truncated>0</truncated>
		<difficult>0</difficult>
		<bndbox>
			<xmin>578</xmin>
			<ymin>718</ymin>
			<xmax>638</xmax>
			<ymax>896</ymax>
		</bndbox>
	</object>
	<object>
		<name>nothing</name>
		<pose>Unspecified</pose>
		<truncated>0</truncated>
		<difficult>0</difficult>
		<bndbox>
			<xmin>727</xmin>
			<ymin>708</ymin>
			<xmax>787</xmax>
			<ymax>886</ymax>
		</bndbox>
	</object>
	<object>
		<name>nothing</name>
		<pose>Unspecified</pose>
		<truncated>0</truncated>
		<difficult>0</difficult>
		<bndbox>
			<xmin>892</xmin>
			<ymin>714</ymin>
			<xmax>952</xmax>
			<ymax>892</ymax>
		</bndbox>
	</object>
	<object>
		<name>nothing</name>
		<pose>Unspecified</pose>
		<truncated>0</truncated>
		<difficult>0</difficult>
		<bndbox>
			<xmin>1046</xmin>
			<ymin>706</ymin>
			<xmax>1106</xmax>
			<ymax>884</ymax>
		</bndbox>
	</object>
	<object>
		<name>nothing</name>
		<pose>Unspecified</pose>
		<truncated>0</truncated>
		<difficult>0</difficult>
		<bndbox>
			<xmin>1194</xmin>
			<ymin>706</ymin>
			<xmax>1254</xmax>
			<ymax>884</ymax>
		</bndbox>
	</object>
	<object>
		<name>nothing</name>
		<pose>Unspecified</pose>
		<truncated>0</truncated>
		<difficult>0</difficult>
		<bndbox>
			<xmin>1360</xmin>
			<ymin>689</ymin>
			<xmax>1420</xmax>
			<ymax>867</ymax>
		</bndbox>
	</object>
	<object>
		<name>nothing</name>
		<pose>Unspecified</pose>
		<truncated>0</truncated>
		<difficult>0</difficult>
		<bndbox>
			<xmin>1511</xmin>
			<ymin>693</ymin>
			<xmax>1571</xmax>
			<ymax>871</ymax>
		</bndbox>
	</object>
	<object>
		<name>nothing</name>
		<pose>Unspecified</pose>
		<truncated>0</truncated>
		<difficult>0</difficult>
		<bndbox>
			<xmin>1671</xmin>
			<ymin>689</ymin>
			<xmax>1731</xmax>
			<ymax>867</ymax>
		</bndbox>
	</object>
	<object>
		<name>nothing</name>
		<pose>Unspecified</pose>
		<truncated>0</truncated>
		<difficult>0</difficult>
		<bndbox>
			<xmin>488</xmin>
			<ymin>1206</ymin>
			<xmax>567</xmax>
			<ymax>1403</ymax>
		</bndbox>
	</object>
	<object>
		<name>nothing</name>
		<pose>Unspecified</pose>
		<truncated>0</truncated>
		<difficult>0</difficult>
		<bndbox>
			<xmin>662</xmin>
			<ymin>1198</ymin>
			<xmax>741</xmax>
			<ymax>1395</ymax>
		</bndbox>
	</object>
	<object>
		<name>on</name>
		<pose>Unspecified</pose>
		<truncated>0</truncated>
		<difficult>0</difficult>
		<bndbox>
			<xmin>1827</xmin>
			<ymin>678</ymin>
			<xmax>1905</xmax>
			<ymax>865</ymax>
		</bndbox>
	</object>
	<object>
		<name>on</name>
		<pose>Unspecified</pose>
		<truncated>0</truncated>
		<difficult>0</difficult>
		<bndbox>
			<xmin>1850</xmin>
			<ymin>927</ymin>
			<xmax>1928</xmax>
			<ymax>1114</ymax>
		</bndbox>
	</object>
	<object>
		<name>on</name>
		<pose>Unspecified</pose>
		<truncated>0</truncated>
		<difficult>0</difficult>
		<bndbox>
			<xmin>1678</xmin>
			<ymin>927</ymin>
			<xmax>1756</xmax>
			<ymax>1114</ymax>
		</bndbox>
	</object>
	<object>
		<name>on</name>
		<pose>Unspecified</pose>
		<truncated>0</truncated>
		<difficult>0</difficult>
		<bndbox>
			<xmin>1518</xmin>
			<ymin>931</ymin>
			<xmax>1596</xmax>
			<ymax>1118</ymax>
		</bndbox>
	</object>
	<object>
		<name>on</name>
		<pose>Unspecified</pose>
		<truncated>0</truncated>
		<difficult>0</difficult>
		<bndbox>
			<xmin>1358</xmin>
			<ymin>923</ymin>
			<xmax>1436</xmax>
			<ymax>1110</ymax>
		</bndbox>
	</object>
	<object>
		<name>on</name>
		<pose>Unspecified</pose>
		<truncated>0</truncated>
		<difficult>0</difficult>
		<bndbox>
			<xmin>1195</xmin>
			<ymin>938</ymin>
			<xmax>1273</xmax>
			<ymax>1125</ymax>
		</bndbox>
	</object>
	<object>
		<name>on</name>
		<pose>Unspecified</pose>
		<truncated>0</truncated>
		<difficult>0</difficult>
		<bndbox>
			<xmin>1024</xmin>
			<ymin>940</ymin>
			<xmax>1102</xmax>
			<ymax>1127</ymax>
		</bndbox>
	</object>
	<object>
		<name>on</name>
		<pose>Unspecified</pose>
		<truncated>0</truncated>
		<difficult>0</difficult>
		<bndbox>
			<xmin>865</xmin>
			<ymin>950</ymin>
			<xmax>943</xmax>
			<ymax>1137</ymax>
		</bndbox>
	</object>
	<object>
		<name>on</name>
		<pose>Unspecified</pose>
		<truncated>0</truncated>
		<difficult>0</difficult>
		<bndbox>
			<xmin>695</xmin>
			<ymin>942</ymin>
			<xmax>773</xmax>
			<ymax>1129</ymax>
		</bndbox>
	</object>
	<object>
		<name>on</name>
		<pose>Unspecified</pose>
		<truncated>0</truncated>
		<difficult>0</difficult>
		<bndbox>
			<xmin>527</xmin>
			<ymin>952</ymin>
			<xmax>605</xmax>
			<ymax>1139</ymax>
		</bndbox>
	</object>
	<object>
		<name>on</name>
		<pose>Unspecified</pose>
		<truncated>0</truncated>
		<difficult>0</difficult>
		<bndbox>
			<xmin>822</xmin>
			<ymin>1203</ymin>
			<xmax>900</xmax>
			<ymax>1390</ymax>
		</bndbox>
	</object>
	<object>
		<name>on</name>
		<pose>Unspecified</pose>
		<truncated>0</truncated>
		<difficult>0</difficult>
		<bndbox>
			<xmin>1005</xmin>
			<ymin>1199</ymin>
			<xmax>1083</xmax>
			<ymax>1386</ymax>
		</bndbox>
	</object>
	<object>
		<name>on</name>
		<pose>Unspecified</pose>
		<truncated>0</truncated>
		<difficult>0</difficult>
		<bndbox>
			<xmin>1177</xmin>
			<ymin>1203</ymin>
			<xmax>1255</xmax>
			<ymax>1390</ymax>
		</bndbox>
	</object>
	<object>
		<name>on</name>
		<pose>Unspecified</pose>
		<truncated>0</truncated>
		<difficult>0</difficult>
		<bndbox>
			<xmin>1350</xmin>
			<ymin>1193</ymin>
			<xmax>1428</xmax>
			<ymax>1380</ymax>
		</bndbox>
	</object>
	<object>
		<name>on</name>
		<pose>Unspecified</pose>
		<truncated>0</truncated>
		<difficult>0</difficult>
		<bndbox>
			<xmin>1522</xmin>
			<ymin>1193</ymin>
			<xmax>1600</xmax>
			<ymax>1380</ymax>
		</bndbox>
	</object>
	<object>
		<name>on</name>
		<pose>Unspecified</pose>
		<truncated>0</truncated>
		<difficult>0</difficult>
		<bndbox>
			<xmin>1709</xmin>
			<ymin>1201</ymin>
			<xmax>1787</xmax>
			<ymax>1388</ymax>
		</bndbox>
	</object>
	<object>
		<name>on</name>
		<pose>Unspecified</pose>
		<truncated>0</truncated>
		<difficult>0</difficult>
		<bndbox>
			<xmin>1877</xmin>
			<ymin>1187</ymin>
			<xmax>1970</xmax>
			<ymax>1378</ymax>
		</bndbox>
	</object>
</annotation>
