<annotation verified="yes">
	<folder>华伟图像处理</folder>
	<filename>IMG_1570(2).jpg</filename>
	<path>C:\Users\Lenovo\Desktop\华伟图像处理\IMG_1570(2).jpg</path>
	<source>
		<database>Unknown</database>
	</source>
	<size>
		<width>2286</width>
		<height>1491</height>
		<depth>3</depth>
	</size>
	<segmented>0</segmented>
	<object>
		<name>nothing</name>
		<pose>Unspecified</pose>
		<truncated>0</truncated>
		<difficult>0</difficult>
		<bndbox>
			<xmin>478</xmin>
			<ymin>394</ymin>
			<xmax>555</xmax>
			<ymax>616</ymax>
		</bndbox>
	</object>
	<object>
		<name>nothing</name>
		<pose>Unspecified</pose>
		<truncated>0</truncated>
		<difficult>0</difficult>
		<bndbox>
			<xmin>637</xmin>
			<ymin>396</ymin>
			<xmax>714</xmax>
			<ymax>618</ymax>
		</bndbox>
	</object>
	<object>
		<name>nothing</name>
		<pose>Unspecified</pose>
		<truncated>0</truncated>
		<difficult>0</difficult>
		<bndbox>
			<xmin>810</xmin>
			<ymin>388</ymin>
			<xmax>887</xmax>
			<ymax>610</ymax>
		</bndbox>
	</object>
	<object>
		<name>nothing</name>
		<pose>Unspecified</pose>
		<truncated>0</truncated>
		<difficult>0</difficult>
		<bndbox>
			<xmin>963</xmin>
			<ymin>389</ymin>
			<xmax>1040</xmax>
			<ymax>611</ymax>
		</bndbox>
	</object>
	<object>
		<name>nothing</name>
		<pose>Unspecified</pose>
		<truncated>0</truncated>
		<difficult>0</difficult>
		<bndbox>
			<xmin>1135</xmin>
			<ymin>394</ymin>
			<xmax>1212</xmax>
			<ymax>616</ymax>
		</bndbox>
	</object>
	<object>
		<name>nothing</name>
		<pose>Unspecified</pose>
		<truncated>0</truncated>
		<difficult>0</difficult>
		<bndbox>
			<xmin>1294</xmin>
			<ymin>381</ymin>
			<xmax>1371</xmax>
			<ymax>603</ymax>
		</bndbox>
	</object>
	<object>
		<name>nothing</name>
		<pose>Unspecified</pose>
		<truncated>0</truncated>
		<difficult>0</difficult>
		<bndbox>
			<xmin>1464</xmin>
			<ymin>383</ymin>
			<xmax>1541</xmax>
			<ymax>605</ymax>
		</bndbox>
	</object>
	<object>
		<name>nothing</name>
		<pose>Unspecified</pose>
		<truncated>0</truncated>
		<difficult>0</difficult>
		<bndbox>
			<xmin>448</xmin>
			<ymin>635</ymin>
			<xmax>525</xmax>
			<ymax>857</ymax>
		</bndbox>
	</object>
	<object>
		<name>nothing</name>
		<pose>Unspecified</pose>
		<truncated>0</truncated>
		<difficult>0</difficult>
		<bndbox>
			<xmin>614</xmin>
			<ymin>648</ymin>
			<xmax>691</xmax>
			<ymax>870</ymax>
		</bndbox>
	</object>
	<object>
		<name>nothing</name>
		<pose>Unspecified</pose>
		<truncated>0</truncated>
		<difficult>0</difficult>
		<bndbox>
			<xmin>779</xmin>
			<ymin>627</ymin>
			<xmax>856</xmax>
			<ymax>849</ymax>
		</bndbox>
	</object>
	<object>
		<name>nothing</name>
		<pose>Unspecified</pose>
		<truncated>0</truncated>
		<difficult>0</difficult>
		<bndbox>
			<xmin>955</xmin>
			<ymin>634</ymin>
			<xmax>1032</xmax>
			<ymax>856</ymax>
		</bndbox>
	</object>
	<object>
		<name>nothing</name>
		<pose>Unspecified</pose>
		<truncated>0</truncated>
		<difficult>0</difficult>
		<bndbox>
			<xmin>1133</xmin>
			<ymin>630</ymin>
			<xmax>1210</xmax>
			<ymax>852</ymax>
		</bndbox>
	</object>
	<object>
		<name>nothing</name>
		<pose>Unspecified</pose>
		<truncated>0</truncated>
		<difficult>0</difficult>
		<bndbox>
			<xmin>1302</xmin>
			<ymin>632</ymin>
			<xmax>1379</xmax>
			<ymax>854</ymax>
		</bndbox>
	</object>
	<object>
		<name>nothing</name>
		<pose>Unspecified</pose>
		<truncated>0</truncated>
		<difficult>0</difficult>
		<bndbox>
			<xmin>374</xmin>
			<ymin>1184</ymin>
			<xmax>451</xmax>
			<ymax>1406</ymax>
		</bndbox>
	</object>
	<object>
		<name>nothing</name>
		<pose>Unspecified</pose>
		<truncated>0</truncated>
		<difficult>0</difficult>
		<bndbox>
			<xmin>543</xmin>
			<ymin>1189</ymin>
			<xmax>641</xmax>
			<ymax>1414</ymax>
		</bndbox>
	</object>
	<object>
		<name>on</name>
		<pose>Unspecified</pose>
		<truncated>0</truncated>
		<difficult>0</difficult>
		<bndbox>
			<xmin>1487</xmin>
			<ymin>625</ymin>
			<xmax>1573</xmax>
			<ymax>837</ymax>
		</bndbox>
	</object>
	<object>
		<name>on</name>
		<pose>Unspecified</pose>
		<truncated>0</truncated>
		<difficult>0</difficult>
		<bndbox>
			<xmin>1656</xmin>
			<ymin>642</ymin>
			<xmax>1742</xmax>
			<ymax>854</ymax>
		</bndbox>
	</object>
	<object>
		<name>on</name>
		<pose>Unspecified</pose>
		<truncated>0</truncated>
		<difficult>0</difficult>
		<bndbox>
			<xmin>1830</xmin>
			<ymin>620</ymin>
			<xmax>1916</xmax>
			<ymax>832</ymax>
		</bndbox>
	</object>
	<object>
		<name>on</name>
		<pose>Unspecified</pose>
		<truncated>0</truncated>
		<difficult>0</difficult>
		<bndbox>
			<xmin>407</xmin>
			<ymin>899</ymin>
			<xmax>493</xmax>
			<ymax>1111</ymax>
		</bndbox>
	</object>
	<object>
		<name>on</name>
		<pose>Unspecified</pose>
		<truncated>0</truncated>
		<difficult>0</difficult>
		<bndbox>
			<xmin>579</xmin>
			<ymin>901</ymin>
			<xmax>665</xmax>
			<ymax>1113</ymax>
		</bndbox>
	</object>
	<object>
		<name>on</name>
		<pose>Unspecified</pose>
		<truncated>0</truncated>
		<difficult>0</difficult>
		<bndbox>
			<xmin>764</xmin>
			<ymin>896</ymin>
			<xmax>850</xmax>
			<ymax>1108</ymax>
		</bndbox>
	</object>
	<object>
		<name>on</name>
		<pose>Unspecified</pose>
		<truncated>0</truncated>
		<difficult>0</difficult>
		<bndbox>
			<xmin>1123</xmin>
			<ymin>901</ymin>
			<xmax>1209</xmax>
			<ymax>1113</ymax>
		</bndbox>
	</object>
	<object>
		<name>on</name>
		<pose>Unspecified</pose>
		<truncated>0</truncated>
		<difficult>0</difficult>
		<bndbox>
			<xmin>1322</xmin>
			<ymin>898</ymin>
			<xmax>1408</xmax>
			<ymax>1110</ymax>
		</bndbox>
	</object>
	<object>
		<name>on</name>
		<pose>Unspecified</pose>
		<truncated>0</truncated>
		<difficult>0</difficult>
		<bndbox>
			<xmin>1489</xmin>
			<ymin>899</ymin>
			<xmax>1575</xmax>
			<ymax>1111</ymax>
		</bndbox>
	</object>
	<object>
		<name>on</name>
		<pose>Unspecified</pose>
		<truncated>0</truncated>
		<difficult>0</difficult>
		<bndbox>
			<xmin>1686</xmin>
			<ymin>889</ymin>
			<xmax>1772</xmax>
			<ymax>1101</ymax>
		</bndbox>
	</object>
	<object>
		<name>on</name>
		<pose>Unspecified</pose>
		<truncated>0</truncated>
		<difficult>0</difficult>
		<bndbox>
			<xmin>1856</xmin>
			<ymin>889</ymin>
			<xmax>1942</xmax>
			<ymax>1101</ymax>
		</bndbox>
	</object>
	<object>
		<name>on</name>
		<pose>Unspecified</pose>
		<truncated>0</truncated>
		<difficult>0</difficult>
		<bndbox>
			<xmin>758</xmin>
			<ymin>1188</ymin>
			<xmax>844</xmax>
			<ymax>1400</ymax>
		</bndbox>
	</object>
	<object>
		<name>on</name>
		<pose>Unspecified</pose>
		<truncated>0</truncated>
		<difficult>0</difficult>
		<bndbox>
			<xmin>925</xmin>
			<ymin>1186</ymin>
			<xmax>1011</xmax>
			<ymax>1398</ymax>
		</bndbox>
	</object>
	<object>
		<name>on</name>
		<pose>Unspecified</pose>
		<truncated>0</truncated>
		<difficult>0</difficult>
		<bndbox>
			<xmin>1119</xmin>
			<ymin>1183</ymin>
			<xmax>1205</xmax>
			<ymax>1395</ymax>
		</bndbox>
	</object>
	<object>
		<name>on</name>
		<pose>Unspecified</pose>
		<truncated>0</truncated>
		<difficult>0</difficult>
		<bndbox>
			<xmin>1317</xmin>
			<ymin>1181</ymin>
			<xmax>1403</xmax>
			<ymax>1393</ymax>
		</bndbox>
	</object>
	<object>
		<name>on</name>
		<pose>Unspecified</pose>
		<truncated>0</truncated>
		<difficult>0</difficult>
		<bndbox>
			<xmin>1517</xmin>
			<ymin>1176</ymin>
			<xmax>1603</xmax>
			<ymax>1388</ymax>
		</bndbox>
	</object>
	<object>
		<name>on</name>
		<pose>Unspecified</pose>
		<truncated>0</truncated>
		<difficult>0</difficult>
		<bndbox>
			<xmin>1702</xmin>
			<ymin>1175</ymin>
			<xmax>1788</xmax>
			<ymax>1387</ymax>
		</bndbox>
	</object>
	<object>
		<name>on</name>
		<pose>Unspecified</pose>
		<truncated>0</truncated>
		<difficult>0</difficult>
		<bndbox>
			<xmin>1899</xmin>
			<ymin>1178</ymin>
			<xmax>1985</xmax>
			<ymax>1390</ymax>
		</bndbox>
	</object>
	<object>
		<name>nothing</name>
		<pose>Unspecified</pose>
		<truncated>0</truncated>
		<difficult>0</difficult>
		<bndbox>
			<xmin>958</xmin>
			<ymin>902</ymin>
			<xmax>1035</xmax>
			<ymax>1124</ymax>
		</bndbox>
	</object>
</annotation>
